Metadata-Version: 2.1
Name: binaryPy
Version: 1.0.5
Summary: binaryPy encryption
Home-page: https://github.com/xqlip/binaryPy
Author: XiaoQingLin
Author-email: xiaoqinglin2018@gmail.com
License: MIT
Platform: UNKNOWN
Classifier: Programming Language :: Python :: 3
